pywats/__init__.py
pywats/async_wats.py
pywats/exceptions.py
pywats/py.typed
pywats/pywats.py
pywats/sync.py
pywats/core/__init__.py
pywats/core/async_client.py
pywats/core/cache.py
pywats/core/client.py
pywats/core/coalesce.py
pywats/core/config.py
pywats/core/exceptions.py
pywats/core/logging.py
pywats/core/pagination.py
pywats/core/parallel.py
pywats/core/performance.py
pywats/core/retry.py
pywats/core/retry_handler.py
pywats/core/routes.py
pywats/core/station.py
pywats/core/sync_runner.py
pywats/core/throttle.py
pywats/core/validation.py
pywats/domains/__init__.py
pywats/domains/analytics/__init__.py
pywats/domains/analytics/async_repository.py
pywats/domains/analytics/async_service.py
pywats/domains/analytics/enums.py
pywats/domains/analytics/models.py
pywats/domains/asset/__init__.py
pywats/domains/asset/async_repository.py
pywats/domains/asset/async_service.py
pywats/domains/asset/enums.py
pywats/domains/asset/models.py
pywats/domains/process/__init__.py
pywats/domains/process/async_repository.py
pywats/domains/process/async_service.py
pywats/domains/process/models.py
pywats/domains/product/__init__.py
pywats/domains/product/async_box_build.py
pywats/domains/product/async_repository.py
pywats/domains/product/async_service.py
pywats/domains/product/box_build.py
pywats/domains/product/enums.py
pywats/domains/product/models.py
pywats/domains/product/sync_box_build.py
pywats/domains/production/__init__.py
pywats/domains/production/async_repository.py
pywats/domains/production/async_service.py
pywats/domains/production/enums.py
pywats/domains/production/models.py
pywats/domains/report/__init__.py
pywats/domains/report/async_repository.py
pywats/domains/report/async_service.py
pywats/domains/report/enums.py
pywats/domains/report/filter_builders.py
pywats/domains/report/import_mode.py
pywats/domains/report/models.py
pywats/domains/report/query_helpers.py
pywats/domains/report/report_models/__init__.py
pywats/domains/report/report_models/additional_data.py
pywats_api-0.2.0b3.dist-info/licenses/LICENSE
pywats_api-0.2.0b3.dist-info/METADATA
pywats_api-0.2.0b3.dist-info/WHEEL
pywats_api-0.2.0b3.dist-info/entry_points.txt
pywats_api-0.2.0b3.dist-info/top_level.txt
pywats_api-0.2.0b3.dist-info/RECORD
