Metadata-Version: 2.4
Name: pywats-api
Version: 0.2.0b3
Summary: Python API library for WATS - manufacturing test data management
Author-email: Virinco AS <support@virinco.com>
Maintainer-email: Virinco AS <support@virinco.com>
License: MIT License
Project-URL: Homepage, https://github.com/olreppe/pyWATS
Project-URL: Documentation, https://github.com/olreppe/pyWATS#readme
Project-URL: Repository, https://github.com/olreppe/pyWATS
Project-URL: Issues, https://github.com/olreppe/pyWATS/issues
Project-URL: Changelog, https://github.com/olreppe/pyWATS/blob/main/CHANGELOG.md
Keywords: wats,test-automation,manufacturing,test-data,api,ai-coded
Classifier: Development Status :: 4 - Beta
Classifier: Intended Audience :: Developers
Classifier: Intended Audience :: Manufacturing
Classifier: Topic :: Software Development :: Testing
Classifier: Topic :: Scientific/Engineering
Classifier: License :: OSI Approved :: MIT License
Classifier: Programming Language :: Python :: 3
Classifier: Programming Language :: Python :: 3.10
Classifier: Programming Language :: Python :: 3.11
Classifier: Programming Language :: Python :: 3.12
Classifier: Programming Language :: Python :: 3.13
Classifier: Operating System :: OS Independent
Classifier: Typing :: Typed
Requires-Python: >=3.10
License-File: LICENSE
Requires-Dist: httpx[http2]>=0.24.0
Requires-Dist: pydantic>=2.0.0
Requires-Dist: python-dateutil>=2.8.0
Requires-Dist: attrs>=22.0.0
Requires-Dist: typing-extensions>=4.8.0; python_version < "3.11"
Provides-Extra: client
Requires-Dist: PySide6>=6.4.0; extra == "client"
Requires-Dist: watchdog>=3.0.0; extra == "client"
Requires-Dist: aiofiles>=23.0.0; extra == "client"
Requires-Dist: qasync>=0.27.0; extra == "client"
Requires-Dist: pywin32>=306; sys_platform == "win32" and extra == "client"
Provides-Extra: client-headless
Requires-Dist: watchdog>=3.0.0; extra == "client-headless"
Requires-Dist: aiofiles>=23.0.0; extra == "client-headless"
Requires-Dist: pywin32>=306; sys_platform == "win32" and extra == "client-headless"
Provides-Extra: dev
Requires-Dist: pytest>=7.0; extra == "dev"
Requires-Dist: pytest-cov>=4.0; extra == "dev"
Requires-Dist: black>=22.0; extra == "dev"
Requires-Dist: isort>=5.0; extra == "dev"
Requires-Dist: flake8>=5.0; extra == "dev"
Requires-Dist: mypy>=1.0; extra == "dev"
Provides-Extra: docs
Requires-Dist: sphinx>=5.0; extra == "docs"
Requires-Dist: sphinx-rtd-theme>=1.0; extra == "docs"
Requires-Dist: sphinx-autodoc-typehints>=1.0; extra == "docs"
Requires-Dist: myst-parser>=0.18; extra == "docs"
Dynamic: license-file
